vscolabi/__init__.py
vs_colabi-1.1.6.dist-info/METADATA
vs_colabi-1.1.6.dist-info/WHEEL
vs_colabi-1.1.6.dist-info/top_level.txt
vs_colabi-1.1.6.dist-info/RECORD
