Metadata-Version: 2.1
Name: vs-colabi
Version: 1.1.6
Summary: Run vs code tunnel inside colab notebook
Home-page: https://gitlab.com/isampypi/vs-colabi
Author: Mhadhbi Issam
Author-email: mhadhbixissam@gmail.com
Classifier: Programming Language :: Python :: 3
Classifier: License :: OSI Approved :: MIT License
Classifier: Operating System :: OS Independent
Requires-Dist: bashi
